{
	"Abj": "Abjasio",
    "Ale": "Alemán",
    "Ara": "Árabe",
    "Aro": "Arameo",
    "Ben": "Bengalí",
    "Bos": "Bosnio",
    "Can": "Cantonés",
    "Che": "Checo",
    "Chi": "Chino",
    "Cor": "Coreano",
    "Dan": "Danés",
    "Esl": "Esloveno",
    "Esp": "Español",
    "Est": "Estonio",
    "Eus": "Euskera",
    "Fra": "Francés",
	"Geo": "Georgiano",
    "Gri": "Griego",
    "Heb": "Hebreo",
    "Hin": "Hindú",
    "Hol": "Holandés",
    "Hun": "Húngaro",
    "Ind": "Indonesio",
    "Ing": "Inglés",
    "Ira": "Iraní",
    "Isl": "Islandés",
    "Ita": "Italiano",
    "Jap": "Japonés",
    "Jem": "Jemer",
    "Kur": "Kurdo",
    "Lat": "Latín",
    "Mac": "Macedonio",
    "Man": "Mandarín",
    "May": "Maya",
    "Muda": "Muda",
    "Nor": "Noruego",
    "Per": "Persa",
    "Pol": "Polaco",
    "Por": "Portugués",
    "Rum": "Rumano",
    "Rus": "Ruso",
    "Ser": "Serbio",
    "Sue": "Sueco",
    "Tai": "Tailandés",
	"Tur": "Turco",
    "Varios": "Varios",
    "Vie": "Vietnamita",
    "Way": "Wayú"
}